git_message_hook/__init__.py
git_message_hook/main.py
git_message_hook/git-templates/hooks/commit-msg
git_message_hook-1.1.1.dist-info/LICENSE
git_message_hook-1.1.1.dist-info/METADATA
git_message_hook-1.1.1.dist-info/WHEEL
git_message_hook-1.1.1.dist-info/entry_points.txt
git_message_hook-1.1.1.dist-info/top_level.txt
git_message_hook-1.1.1.dist-info/RECORD
