Metadata-Version: 2.1
Name: git-message-hook
Version: 1.1.1
Summary: Force conventional git commit messages for git repositories, by leveraging git hooks.
Home-page: https://github.com/oscar-defelice/git-message-hook
Author: Oscar de Felice
Author-email: oscar.defelice@gmail.com
License: MIT
Keywords: security,scanner
Classifier: Programming Language :: Python :: 3
Classifier: License :: OSI Approved :: MIT License
Classifier: Operating System :: OS Independent
Requires-Python: >= 3.4
License-File: LICENSE
